lazydog_merge_sqlite/__init__.py
lazydog_merge_sqlite/__main__.py
lazydog_merge_sqlite/merge_sqlite.py
lazydog_merge_sqlite-0.1.0.dist-info/LICENSE.txt
lazydog_merge_sqlite-0.1.0.dist-info/METADATA
lazydog_merge_sqlite-0.1.0.dist-info/WHEEL
lazydog_merge_sqlite-0.1.0.dist-info/entry_points.txt
lazydog_merge_sqlite-0.1.0.dist-info/top_level.txt
lazydog_merge_sqlite-0.1.0.dist-info/RECORD
