Metadata-Version: 2.1
Name: lazydog-merge-sqlite
Version: 0.1.0
Summary: Merge sqlite db files
Author-email: Francis Hillman <dj.after.burn@gmail.com>
License: EUPL-1.2
Project-URL: Repository, https://github.com/FransHeuvelmans/Lazydog
Classifier: Development Status :: 3 - Alpha
Classifier: Programming Language :: Python :: 3.10
Classifier: Environment :: Console
Classifier: Topic :: Database
Requires-Python: >=3.10
License-File: LICENSE.txt
